{"version": 0.6, "generator": "Overpass API 0.7.62.8 e802775f", "osm3s": {"timestamp_osm_base": "2025-09-13T03:04:09Z", "copyright": "The data included in this document is from www.openstreetmap.org. The data is made available under ODbL."}, "elements": [{"type": "node", "id": 5767091053, "lat": -15.9393552, "lon": -64.7574857, "tags": {"addr:city": "Santa Rosa la Boca de Chapare", "amenity": "hospital", "description": "Centro de Salud 1er Nivel \nMinSalud CODSNIS 300651", "emergency": "yes", "healthcare": "hospital", "healthcare:speciality": "general", "name": "C.S. Santa Rosa de la Boca del Chapare", "operator": "Ministerio de Salud y Deportes", "operator:short": "MinSalud", "operator:type": "government", "operator:wikidata": "Q44225411"}}]}